odoo9_addon_account_payment_show_invoice-9.0.1.0.0-py2.7-nspkg.pth
odoo9_addon_account_payment_show_invoice-9.0.1.0.0.dist-info/DESCRIPTION.rst
odoo9_addon_account_payment_show_invoice-9.0.1.0.0.dist-info/METADATA
odoo9_addon_account_payment_show_invoice-9.0.1.0.0.dist-info/RECORD
odoo9_addon_account_payment_show_invoice-9.0.1.0.0.dist-info/WHEEL
odoo9_addon_account_payment_show_invoice-9.0.1.0.0.dist-info/metadata.json
odoo9_addon_account_payment_show_invoice-9.0.1.0.0.dist-info/namespace_packages.txt
odoo9_addon_account_payment_show_invoice-9.0.1.0.0.dist-info/top_level.txt
odoo_addons/account_payment_show_invoice/README.rst
odoo_addons/account_payment_show_invoice/__init__.py
odoo_addons/account_payment_show_invoice/__openerp__.py
odoo_addons/account_payment_show_invoice/models/__init__.py
odoo_addons/account_payment_show_invoice/models/account_payment.py
odoo_addons/account_payment_show_invoice/static/description/icon.png
odoo_addons/account_payment_show_invoice/static/description/payments_view.png
odoo_addons/account_payment_show_invoice/views/account_payment_view.xml
