Metadata-Version: 2.0
Name: odoo9-addon-account-payment-show-invoice
Version: 9.0.1.0.0
Summary: Extends the tree view of payments to show the paid invoices related to the payments using the vendor reference by default
Home-page: https://odoo-community.org/
Author: Eficent, Odoo Community Association (OCA)
Author-email: support@odoo-community.org
License: AGPL-3
Platform: UNKNOWN
Classifier: Programming Language :: Python :: 2.7
Classifier: Framework :: Odoo
Classifier: License :: OSI Approved :: GNU Affero General Public License v3
Requires-Dist: odoo (<9.1a,>=9.0a)
